{
  "moduleName": "Checkbox",
  "filePath": "src/lib/Input/Checkbox.svelte",
  "props": [
    {
      "name": "htmlElement",
      "kind": "let",
      "type": "null | HTMLInputElement",
      "value": "null",
      "isFunction": false,
      "isFunctionDeclaration": false,
      "isRequired": false,
      "constant": false,
      "reactive": true
    },
    {
      "name": "name",
      "kind": "let",
      "type": "string",
      "value": "''",
      "isFunction": false,
      "isFunctionDeclaration": false,
      "isRequired": false,
      "constant": false,
      "reactive": false
    },
    {
      "name": "checked",
      "kind": "let",
      "type": "boolean",
      "value": "false",
      "isFunction": false,
      "isFunctionDeclaration": false,
      "isRequired": false,
      "constant": false,
      "reactive": true
    }
  ],
  "moduleExports": [],
  "slots": [{ "name": "__default__", "default": true, "slot_props": "{}" }],
  "events": [{ "type": "forwarded", "name": "click", "element": "input" }],
  "typedefs": []
}
